desonglll_latex_font/__init__.py
desonglll_latex_font/desonglll_latex_font.py
desonglll_latex_font-0.1.1.dist-info/AUTHORS.rst
desonglll_latex_font-0.1.1.dist-info/LICENSE
desonglll_latex_font-0.1.1.dist-info/METADATA
desonglll_latex_font-0.1.1.dist-info/WHEEL
desonglll_latex_font-0.1.1.dist-info/entry_points.txt
desonglll_latex_font-0.1.1.dist-info/top_level.txt
desonglll_latex_font-0.1.1.dist-info/RECORD
