Metadata-Version: 2.1
Name: desonglll_latex_font
Version: 0.1.1
Summary: Font installation for my latex template requirement.
Author-email: Lin Desong <lindesong666@gmail.com>
Maintainer-email: Lin Desong <lindesong666@gmail.com>
License: MIT license
Project-URL: bugs, https://github.com/desonglll/desonglll_latex_font/issues
Project-URL: changelog, https://github.com/desonglll/desonglll_latex_font/blob/master/changelog.md
Project-URL: homepage, https://github.com/desonglll/desonglll_latex_font
License-File: LICENSE
License-File: AUTHORS.rst
Requires-Dist: requests
Provides-Extra: dev
Requires-Dist: coverage; extra == "dev"
Requires-Dist: mypy; extra == "dev"
Requires-Dist: pytest; extra == "dev"
Requires-Dist: ruff; extra == "dev"
